collective.base64imagepatch-0.13-py2.7-nspkg.pth
collective/base64imagepatch/__init__.py
collective/base64imagepatch/configure.zcml
collective/base64imagepatch/patch.py
collective/base64imagepatch/patch_all_view.py
collective/base64imagepatch/subscribers.py
collective/base64imagepatch/tests.py
collective.base64imagepatch-0.13.dist-info/METADATA
collective.base64imagepatch-0.13.dist-info/WHEEL
collective.base64imagepatch-0.13.dist-info/entry_points.txt
collective.base64imagepatch-0.13.dist-info/namespace_packages.txt
collective.base64imagepatch-0.13.dist-info/paster_plugins.txt
collective.base64imagepatch-0.13.dist-info/top_level.txt
collective.base64imagepatch-0.13.dist-info/RECORD
