Metadata-Version: 2.1
Name: collective.base64imagepatch
Version: 0.13
Summary: Turn inline images in rich text into actual image objects
Home-page: https://github.com/collective/collective.base64imagepatch
Author: Alexander Loechel
Author-email: Alexander.Loechel@lmu.de
License: GPL
Keywords: zope plone base64 image patcher
Platform: UNKNOWN
Classifier: Development Status :: 5 - Production/Stable
Classifier: Framework :: Plone
Classifier: Framework :: Plone :: 4.3
Classifier: License :: OSI Approved :: GNU General Public License (GPL)
Classifier: Programming Language :: Python
Classifier: Programming Language :: Python :: 2.7
Requires-Dist: setuptools
Requires-Dist: beautifulsoup4
Provides-Extra: test
Requires-Dist: Products.PloneTestCase ; extra == 'test'
Requires-Dist: plone.app.testing[robot] ; extra == 'test'
Requires-Dist: plone.app.robotframework ; extra == 'test'
Requires-Dist: Products.ATContentTypes ; extra == 'test'
Requires-Dist: Products.contentmigration ; extra == 'test'
Requires-Dist: plone.app.contenttypes ; extra == 'test'
